{
  "id": "883197",
  "is_channel": false,
  "thumbnail": {
    "url": "https://static-cdn77.xnxx-cdn.com/img/lightbox/lightbox-blank.gif",
    "idcdn": "10",
    "video_id": "883197",
    "alt": ""
  },
  "link": {
    "href": "/video-ixh9b6/embarazada_re_putisima",
    "title": "Embarazada Re' Putisima"
  },
  "uploader": {
    "name": "",
    "profile_url": ""
  },
  "metadata": {
    "views": "1.4M",
    "rating": "100%",
    "duration": "21min",
    "quality": " 480p"
  },
  "meta_data": {
    "mp4": "https://cdn77-vid-mp4.xnxx-cdn.com/L55OqEqElEimiAFfW7tGKg==,1750079706/videos/mp4/7/6/b/xvideos.com_76b04caa4c1ad33cd8036cd3777c37e8-2.mp4?ui=MzUuMTk3LjEyLjIyNC0tL3ZpZGVvLWl4aDliNi9wcmVnbmFudF9yZV9wdXRp",
    "url": "https://cdn77-vid.xnxx-cdn.com/bpZ2jZgIyTbd34N0s8hAfQ==,1750079706/videos/hls/76/b0/4c/76b04caa4c1ad33cd8036cd3777c37e8-2/hls.m3u8",
    "thumbnail": "https://cdn77-pic.xnxx-cdn.com/videos/thumbs169xnxxposter/76/b0/4c/76b04caa4c1ad33cd8036cd3777c37e8-2/76b04caa4c1ad33cd8036cd3777c37e8.4.jpg",
    "tags": [
      "anal",
      "cumshot",
      "blowjob",
      "brunette",
      "fingering",
      "threesome",
      "asstomouth",
      "pussyfucking",
      "fetish",
      "pregnant",
      "preggy"
    ]
  }
}